{
    "id":  "quiz-004",
    "tags":  [
                 "operating-systems"
             ],
    "questions":  [
                      {
                          "question":  "What is the main difference between a process and a thread?",
                          "tags":  [
                                       "operating-systems"
                                   ],
                          "difficulty":  "beginner",
                          "explanation":  "Threads share a process address space, while processes have separate address spaces.",
                          "correct_answer":  "Threads share an address space; processes do not",
                          "choices":  [
                                          "Threads share an address space; processes do not",
                                          "Processes are always faster",
                                          "Threads cannot be scheduled",
                                          "Processes have no memory"
                                      ]
                      },
                      {
                          "question":  "Which scheduling algorithm is commonly used for time-sharing systems?",
                          "tags":  [
                                       "operating-systems"
                                   ],
                          "difficulty":  "beginner",
                          "explanation":  "Round Robin gives each process a time slice and is standard for interactive systems.",
                          "correct_answer":  "Round Robin",
                          "choices":  [
                                          "FCFS",
                                          "Round Robin",
                                          "SJF",
                                          "Priority without aging"
                                      ]
                      },
                      {
                          "question":  "What does a context switch do?",
                          "tags":  [
                                       "operating-systems"
                                   ],
                          "difficulty":  "beginner",
                          "explanation":  "A context switch saves and restores CPU state when switching processes or threads.",
                          "correct_answer":  "Saves and restores CPU state",
                          "choices":  [
                                          "Deletes a process",
                                          "Saves and restores CPU state",
                                          "Allocates disk space",
                                          "Compiles a program"
                                      ]
                      },
                      {
                          "question":  "Which is NOT a necessary condition for deadlock?",
                          "tags":  [
                                       "operating-systems"
                                   ],
                          "difficulty":  "beginner",
                          "explanation":  "Deadlock requires mutual exclusion, hold and wait, no preemption, and circular wait. Unlimited resources are not a condition.",
                          "correct_answer":  "Unlimited resources",
                          "choices":  [
                                          "Mutual exclusion",
                                          "Hold and wait",
                                          "No preemption",
                                          "Unlimited resources"
                                      ]
                      },
                      {
                          "question":  "Paging divides memory into: ",
                          "tags":  [
                                       "operating-systems"
                                   ],
                          "difficulty":  "beginner",
                          "explanation":  "Paging uses fixed-size pages and frames.",
                          "correct_answer":  "Fixed-size pages",
                          "choices":  [
                                          "Variable-size segments",
                                          "Fixed-size pages",
                                          "Files",
                                          "Registers only"
                                      ]
                      },
                      {
                          "question":  "What is a system call?",
                          "tags":  [
                                       "operating-systems"
                                   ],
                          "difficulty":  "beginner",
                          "explanation":  "System calls are the interface from user programs to OS services.",
                          "correct_answer":  "An interface to OS services",
                          "choices":  [
                                          "A hardware interrupt",
                                          "An interface to OS services",
                                          "A type of memory",
                                          "A scheduling policy"
                                      ]
                      },
                      {
                          "question":  "What is thrashing?",
                          "tags":  [
                                       "operating-systems"
                                   ],
                          "difficulty":  "beginner",
                          "explanation":  "Thrashing occurs when the system spends most of its time paging rather than doing useful work.",
                          "correct_answer":  "Excessive paging that kills performance",
                          "choices":  [
                                          "A kernel crash",
                                          "Excessive paging that kills performance",
                                          "A fast context switch",
                                          "A file system error"
                                      ]
                      },
                      {
                          "question":  "Which metric measures time from job submission to completion?",
                          "tags":  [
                                       "operating-systems"
                                   ],
                          "difficulty":  "beginner",
                          "explanation":  "Turnaround time includes waiting and execution time.",
                          "correct_answer":  "Turnaround time",
                          "choices":  [
                                          "Response time",
                                          "Turnaround time",
                                          "CPU utilization",
                                          "Throughput"
                                      ]
                      },
                      {
                          "question":  "What does a mutex provide?",
                          "tags":  [
                                       "operating-systems"
                                   ],
                          "difficulty":  "beginner",
                          "explanation":  "A mutex enforces mutual exclusion for critical sections.",
                          "correct_answer":  "Mutual exclusion",
                          "choices":  [
                                          "Deadlock",
                                          "Mutual exclusion",
                                          "Priority scheduling",
                                          "Virtual memory"
                                      ]
                      },
                      {
                          "question":  "What is a daemon process?",
                          "tags":  [
                                       "operating-systems"
                                   ],
                          "difficulty":  "beginner",
                          "explanation":  "Daemons run in the background to provide services.",
                          "correct_answer":  "A background service",
                          "choices":  [
                                          "A user interface",
                                          "A background service",
                                          "A file format",
                                          "A memory leak"
                                      ]
                      }
                  ],
    "difficulty":  "beginner",
    "module":  "Operating Systems",
    "summary":  "Check your understanding of processes, scheduling, and memory basics.",
    "title":  "Operating Systems Quiz 4"
}
