{
    "topic":  "Databases Topic 9",
    "id":  "databases-lesson-09",
    "practice":  [
                     "Describe the main steps of Databases Topic 9.",
                     "Solve a small exercise using Databases Topic 9.",
                     "List two pitfalls and how to avoid them."
                 ],
    "quizzes":  [
                    "quiz-169"
                ],
    "codeSamples":  [
                        {
                            "code":  "Step 1: Define the problem\\nStep 2: Apply Databases Topic 9\\nStep 3: Verify results",
                            "language":  "plaintext"
                        }
                    ],
    "module":  "Databases",
    "title":  "Databases Lesson 9",
    "references":  [
                       "Guide: Databases Topic 9 Essentials",
                       "Cheat Sheet: Databases Basics"
                   ],
    "summary":  "Master Databases Topic 9 with focused objectives, examples, and practice tasks.",
    "difficulty":  "beginner",
    "content":  "# Databases Lesson 9\n\n## Overview\nMaster Databases Topic 9 with focused objectives, examples, and practice tasks.\n\n- Identify core terminology\n- Walk through a guided example\n- Practice with a short task list",
    "examples":  [
                     "Worked example using Databases Topic 9.",
                     "Edge case analysis for Databases Topic 9."
                 ],
    "tags":  [
                 "databases",
                 "lesson"
             ],
    "objectives":  [
                       "Explain key concepts in Databases Topic 9."
                   ]
}
